rtop/__init__.py
rtop/__main__.py
rtop/app.py
rtop/launch.py
rtop/launch_table.py
rtop/schema.py
tests/__init__.py
tests/spec_main.py
rtop-1.0.0.dist-info/LICENSE
rtop-1.0.0.dist-info/METADATA
rtop-1.0.0.dist-info/WHEEL
rtop-1.0.0.dist-info/entry_points.txt
rtop-1.0.0.dist-info/top_level.txt
rtop-1.0.0.dist-info/RECORD
