Metadata-Version: 2.1
Name: rtop
Version: 1.0.0
Summary: A TUI monitor that integrates with RocketLaunch.live to bring a list of upcoming launches.
Home-page: https://github.com/dmitri-mcguckin/rtop
Author: Dmitri McGuckin
License: GPL-3.0
Platform: UNKNOWN
Classifier: Programming Language :: Python :: 3
Classifier: License :: OSI Approved :: GNU General Public License v3 (GPLv3)
Classifier: Operating System :: OS Independent
Classifier: Environment :: Console :: Curses
Classifier: Topic :: Software Development :: User Interfaces
Classifier: Topic :: System :: Monitoring
Requires-Python: >=3
Provides-Extra: dev
Requires-Dist: setuptools ; extra == 'dev'
Requires-Dist: wheel ; extra == 'dev'
Requires-Dist: pytest ; extra == 'dev'
Requires-Dist: flake8 ; extra == 'dev'
Requires-Dist: twine ; extra == 'dev'
Requires-Dist: sphinx ; extra == 'dev'
Requires-Dist: sphinx-rtd-theme ; extra == 'dev'
